bmt_py/__init__.py
bmt_py/__version__.py
bmt_py/chunk.py
bmt_py/file.py
bmt_py/py.typed
bmt_py/span.py
bmt_py/utils.py
bmt_py-0.1.3.dist-info/METADATA
bmt_py-0.1.3.dist-info/WHEEL
bmt_py-0.1.3.dist-info/licenses/LICENSE
bmt_py-0.1.3.dist-info/RECORD
