Metadata-Version: 2.3
Name: bmt_py
Version: 0.1.3
Summary: Binary Merkle Tree operations on data
Project-URL: Documentation, https://aviksaikat.github.io/bmt_py/
Project-URL: Source, https://github.com/aviksaikat/bmt_py
Author-email: Saikat Karmakar <saikickkarma@protonmail.com>
License: 
License-File: LICENSE
Classifier: Development Status :: 2 - Pre-Alpha
Classifier: Programming Language :: Python
Classifier: Programming Language :: Python :: 3.9
Classifier: Programming Language :: Python :: 3.10
Classifier: Programming Language :: Python :: 3.11
Classifier: Programming Language :: Python :: 3.12
Classifier: Programming Language :: Python :: Implementation :: CPython
Classifier: Programming Language :: Python :: Implementation :: PyPy
Requires-Python: >=3.9
Requires-Dist: eth-utils
Requires-Dist: pycryptodome
Requires-Dist: pydantic
